Metadata-Version: 2.1
Name: fragile
Version: 0.0.60
Summary: Framework for developing FractalAI based algorithms.
Home-page: https://github.com/FragileTech/fragile
Download-URL: https://github.com/FragileTech/fragile
Author: Guillem Duran Ballester
Author-email: info@fragile.tech
License: MIT
Keywords: reinforcement learning,artificial intelligence,monte carlo,planning
Classifier: Development Status :: 3 - Alpha
Classifier: Environment :: Console
Classifier: Intended Audience :: Developers
Classifier: License :: OSI Approved :: MIT License
Classifier: Operating System :: POSIX
Classifier: Programming Language :: Python :: 3.7
Classifier: Programming Language :: Python :: 3.8
Classifier: Programming Language :: Python :: 3.9
Classifier: Topic :: Software Development :: Libraries
License-File: LICENSE
Requires-Dist: einops
Requires-Dist: flogging
Requires-Dist: judo >=0.0.15
Requires-Dist: networkx
Requires-Dist: numba
Requires-Dist: scipy
Requires-Dist: tqdm
Provides-Extra: all
Requires-Dist: atari-py ==0.1.1 ; extra == 'all'
Requires-Dist: opencv-python ; extra == 'all'
Requires-Dist: gym ==0.17.3 ; extra == 'all'
Requires-Dist: pillow-simd ; extra == 'all'
Requires-Dist: plangym >=0.0.31 ; extra == 'all'
Requires-Dist: matplotlib ==3.7.1 ; extra == 'all'
Requires-Dist: bokeh ==2.4.0 ; extra == 'all'
Requires-Dist: pandas ==1.5.3 ; extra == 'all'
Requires-Dist: panel ==0.14.4 ; extra == 'all'
Requires-Dist: holoviews ; extra == 'all'
Requires-Dist: hvplot ; extra == 'all'
Requires-Dist: plotly ; extra == 'all'
Requires-Dist: streamz ; extra == 'all'
Requires-Dist: param ; extra == 'all'
Requires-Dist: selenium ; extra == 'all'
Requires-Dist: pyarrow ; extra == 'all'
Requires-Dist: pytest ==6.2.5 ; extra == 'all'
Requires-Dist: pytest-cov ==3.0.0 ; extra == 'all'
Requires-Dist: pytest-xdist ==2.4.0 ; extra == 'all'
Requires-Dist: pytest-rerunfailures ==10.2 ; extra == 'all'
Requires-Dist: hypothesis ==6.24.6 ; extra == 'all'
Requires-Dist: ray >=1.0.1.post1 ; extra == 'all'
Requires-Dist: setproctitle ; extra == 'all'
Provides-Extra: atari
Requires-Dist: atari-py ==0.1.1 ; extra == 'atari'
Requires-Dist: opencv-python ; extra == 'atari'
Requires-Dist: gym ==0.17.3 ; extra == 'atari'
Requires-Dist: pillow-simd ; extra == 'atari'
Requires-Dist: plangym >=0.0.31 ; extra == 'atari'
Provides-Extra: dataviz
Requires-Dist: matplotlib ==3.7.1 ; extra == 'dataviz'
Requires-Dist: bokeh ==2.4.0 ; extra == 'dataviz'
Requires-Dist: pandas ==1.5.3 ; extra == 'dataviz'
Requires-Dist: panel ==0.14.4 ; extra == 'dataviz'
Requires-Dist: holoviews ; extra == 'dataviz'
Requires-Dist: hvplot ; extra == 'dataviz'
Requires-Dist: plotly ; extra == 'dataviz'
Requires-Dist: streamz ; extra == 'dataviz'
Requires-Dist: param ; extra == 'dataviz'
Requires-Dist: selenium ; extra == 'dataviz'
Requires-Dist: pyarrow ; extra == 'dataviz'
Provides-Extra: ray
Requires-Dist: ray >=1.0.1.post1 ; extra == 'ray'
Requires-Dist: setproctitle ; extra == 'ray'
Provides-Extra: test
Requires-Dist: pytest ==6.2.5 ; extra == 'test'
Requires-Dist: pytest-cov ==3.0.0 ; extra == 'test'
Requires-Dist: pytest-xdist ==2.4.0 ; extra == 'test'
Requires-Dist: pytest-rerunfailures ==10.2 ; extra == 'test'
Requires-Dist: hypothesis ==6.24.6 ; extra == 'test'
